[
  {
    "kw": "best budget wireless keyboard for home office",
    "prod": "Logitech MX Keys Mini, Keychron K3 Pro",
    "used": true
  },
  {
    "kw": "best budget ergonomic keyboard for typing",
    "prod": "Microsoft Sculpt, Logitech Ergo K860",
    "used": true
  },
  {
    "kw": "best budget number pad for laptop",
    "prod": "Keychron Q0, NUUMY Wireless Numpad",
    "used": true
  },
  {
    "kw": "best budget drawing tablet for remote work",
    "prod": "Wacom Intuos Small, XP-Pen Deco",
    "used": true
  },
  {
    "kw": "best budget touchpad for Windows laptop",
    "prod": "Logitech T650, Jelly Comb Touchpad",
    "used": true
  },
  {
    "kw": "best budget speakers for home office",
    "prod": "Creative Pebble V3, Logitech Z207",
    "used": true
  },
  {
    "kw": "best budget earbuds for zoom calls",
    "prod": "EarFun Air Pro 3, Soundcore Liberty 4 NC",
    "used": true
  },
  {
    "kw": "best budget conference speaker for small meetings",
    "prod": "Anker PowerConf, Jabra Speak 410",
    "used": true
  },
  {
    "kw": "best budget soundbar for computer",
    "prod": "Creative Stage V2, Redragon GS560",
    "used": true
  },
  {
    "kw": "best budget DAC for home office audio",
    "prod": "FiiO KA1, AudioQuest DragonFly",
    "used": true
  },
  {
    "kw": "best budget office chair under 200 dollars",
    "prod": "Hbada Office Chair, Amazon Basics Ergonomic",
    "used": true
  },
  {
    "kw": "best budget kneeling chair for posture",
    "prod": "Varier Active, Dragonn Kneeling Chair",
    "used": false
  },
  {
    "kw": "best budget balance ball chair",
    "prod": "Gaiam Balance Ball Chair, Trideer Ball Chair",
    "used": false
  },
  {
    "kw": "best budget standing mat for desk",
    "prod": "CumulusPro Standing Mat, Ergodriven Topo",
    "used": false
  },
  {
    "kw": "best budget under desk keyboard tray",
    "prod": "VIVO Under Desk Tray, Mount-It Tray",
    "used": false
  },
  {
    "kw": "best budget external SSD for work",
    "prod": "Samsung T7, SanDisk Extreme",
    "used": false
  },
  {
    "kw": "best budget USB flash drive for files",
    "prod": "SanDisk Ultra Fit, Samsung BAR Plus",
    "used": false
  },
  {
    "kw": "best budget NAS for home office backup",
    "prod": "Synology DS220j, TerraMaster F2-210",
    "used": false
  },
  {
    "kw": "best budget cloud backup service",
    "prod": "Backblaze, IDrive",
    "used": false
  },
  {
    "kw": "best budget hard drive enclosure",
    "prod": "Sabrent USB 3.0, ORICO Enclosure",
    "used": false
  },
  {
    "kw": "best budget WiFi router for home office",
    "prod": "TP-Link Archer AX55, Asus RT-AX1800S",
    "used": false
  },
  {
    "kw": "best budget WiFi extender for dead zones",
    "prod": "TP-Link RE315, Netgear EX3700",
    "used": false
  },
  {
    "kw": "best budget mesh WiFi system for remote work",
    "prod": "TP-Link Deco X20, Eero 6",
    "used": false
  },
  {
    "kw": "best budget VPN service for workers",
    "prod": "Mullvad, ProtonVPN",
    "used": false
  },
  {
    "kw": "best budget network switch for wired setup",
    "prod": "TP-Link TL-SG105, Netgear GS305",
    "used": false
  },
  {
    "kw": "best budget whiteboard for home office",
    "prod": "U Brands Glass Board, Quartet Dry Erase",
    "used": false
  },
  {
    "kw": "best budget planner notebook for productivity",
    "prod": "Rocketbook Panda Planner, Moleskine Weekly",
    "used": false
  },
  {
    "kw": "best budget sticky note dispenser",
    "prod": "Post-it Dispenser, Amazon Basics Notes",
    "used": false
  },
  {
    "kw": "best budget filing cabinet for home office",
    "prod": "Hirsh 2-Drawer, Lorell Mobile File",
    "used": false
  },
  {
    "kw": "best budget label maker for organization",
    "prod": "Brother PT-D210, DYMO LabelManager",
    "used": false
  },
  {
    "kw": "best budget GaN charger for travel",
    "prod": "Anker Nano II 65W, Baseus GaN 65W",
    "used": false
  },
  {
    "kw": "best budget UPS battery backup",
    "prod": "APC Back-UPS BE600M1, CyberPower CP825",
    "used": false
  },
  {
    "kw": "best budget wireless charging pad for desk",
    "prod": "Anker 313, Belkin BoostCharge",
    "used": false
  },
  {
    "kw": "best budget multi device charger station",
    "prod": "Anker PowerWave, Satechi Charger",
    "used": false
  },
  {
    "kw": "best budget car charger for remote workers",
    "prod": "UGREEN 30W, Baseus 65W Car Charger",
    "used": false
  },
  {
    "kw": "best budget anti fatigue chair cushion",
    "prod": "ComfiLife Gel Cushion, Everlasting Comfort",
    "used": false
  },
  {
    "kw": "best budget neck traction device for desk workers",
    "prod": "Restore Neck Traction, Comfier Neck Massager",
    "used": false
  },
  {
    "kw": "best budget back stretcher for home",
    "prod": "BackBridge, Comfier Back Stretcher",
    "used": false
  },
  {
    "kw": "best budget massage cushion for office chair",
    "prod": "Zyllion Shiatsu, Comfier Massage Cushion",
    "used": false
  },
  {
    "kw": "best budget heating pad for back pain",
    "prod": "Sunbeam Heating Pad, UTK Far Infrared",
    "used": false
  },
  {
    "kw": "best budget graphics tablet for designers",
    "prod": "Huion Inspiroy, XP-Pen Artist 12",
    "used": false
  },
  {
    "kw": "best budget portable second monitor for laptop",
    "prod": "Arzopa Portable Monitor, AOC 16T2",
    "used": false
  },
  {
    "kw": "best budget color calibration tool",
    "prod": "Datacolor Spyder X, X-Rite i1Studio",
    "used": false
  },
  {
    "kw": "best budget ring light for video recording",
    "prod": "NEEWER Ring Light, UBeesize Ring Light",
    "used": false
  },
  {
    "kw": "best budget microphone arm stand",
    "prod": "InnoGear Mic Arm, Neewer NW-35",
    "used": false
  },
  {
    "kw": "best budget smart plug for home office",
    "prod": "Kasa HS103, Amazon Smart Plug",
    "used": false
  },
  {
    "kw": "best budget smart button for productivity",
    "prod": "Flic Smart Button, Logitech Litra Button",
    "used": false
  },
  {
    "kw": "best budget digital picture frame for desk",
    "prod": "Aura Carver, Nixplay Seed",
    "used": false
  },
  {
    "kw": "best budget desk humidifier for dry office",
    "prod": "Levoit LV600S, Everlasting Comfort Humidifier",
    "used": false
  },
  {
    "kw": "best budget desk air purifier",
    "prod": "Levoit Core 200S, Coway Airmega 100",
    "used": false
  }
]